aiofiles-stubs/METADATA.toml
aiofiles-stubs/__init__.pyi
aiofiles-stubs/base.pyi
aiofiles-stubs/os.pyi
aiofiles-stubs/ospath.pyi
aiofiles-stubs/py.typed
aiofiles-stubs/tempfile/__init__.pyi
aiofiles-stubs/tempfile/temptypes.pyi
aiofiles-stubs/threadpool/__init__.pyi
aiofiles-stubs/threadpool/binary.pyi
aiofiles-stubs/threadpool/text.pyi
aiofiles-stubs/threadpool/utils.pyi
types_aiofiles-24.1.0.20250822.dist-info/licenses/LICENSE
types_aiofiles-24.1.0.20250822.dist-info/METADATA
types_aiofiles-24.1.0.20250822.dist-info/WHEEL
types_aiofiles-24.1.0.20250822.dist-info/top_level.txt
types_aiofiles-24.1.0.20250822.dist-info/RECORD
